automation/__init__.py
automation/admin.py
automation/apps.py
automation/consumers.py
automation/data_db_manager.py
automation/db_creation.py
automation/forms.py
automation/models.py
automation/routing.py
automation/script_data.py
automation/script_db_manager.py
automation/script_runner.py
automation/seasion_data_manager.py
automation/test3.py
automation/tests.py
automation/urls.py
automation/views.py
automation/migrations/0001_initial.py
automation/migrations/0002_remove_script_script_data.py
automation/migrations/__init__.py
automation/static/styles.css
automation/static/automation/styles.css
automation/static/css/bootstrap-grid.css
automation/static/css/bootstrap-grid.css.map
automation/static/css/bootstrap-grid.min.css
automation/static/css/bootstrap-grid.min.css.map
automation/static/css/bootstrap-grid.rtl.css
automation/static/css/bootstrap-grid.rtl.css.map
automation/static/css/bootstrap-grid.rtl.min.css
automation/static/css/bootstrap-grid.rtl.min.css.map
automation/static/css/bootstrap-reboot.css
automation/static/css/bootstrap-reboot.css.map
automation/static/css/bootstrap-reboot.min.css
automation/static/css/bootstrap-reboot.min.css.map
automation/static/css/bootstrap-reboot.rtl.css
automation/static/css/bootstrap-reboot.rtl.css.map
automation/static/css/bootstrap-reboot.rtl.min.css
automation/static/css/bootstrap-reboot.rtl.min.css.map
automation/static/css/bootstrap-utilities.css
automation/static/css/bootstrap-utilities.css.map
automation/static/css/bootstrap-utilities.min.css
automation/static/css/bootstrap-utilities.min.css.map
automation/static/css/bootstrap-utilities.rtl.css
automation/static/css/bootstrap-utilities.rtl.css.map
automation/static/css/bootstrap-utilities.rtl.min.css
automation/static/css/bootstrap-utilities.rtl.min.css.map
automation/static/css/bootstrap.css
automation/static/css/bootstrap.css.map
automation/static/css/bootstrap.min.css
automation/static/css/bootstrap.min.css.map
automation/static/css/bootstrap.rtl.css
script_creator-1.2.0.dist-info/METADATA
script_creator-1.2.0.dist-info/WHEEL
script_creator-1.2.0.dist-info/top_level.txt
script_creator-1.2.0.dist-info/RECORD
